setup.py
dil_probability/Binomialdistribution.py
dil_probability/Gaussiandistribution.py
dil_probability/Generaldistribution.py
dil_probability/__init__.py
dil_probability.egg-info/PKG-INFO
dil_probability.egg-info/SOURCES.txt
dil_probability.egg-info/dependency_links.txt
dil_probability.egg-info/not-zip-safe
dil_probability.egg-info/top_level.txt