Metadata-Version: 1.0
Name: dil-probability
Version: 0.1
Summary: Gaussian and Binomial distributions
Home-page: UNKNOWN
Author: Dil
Author-email: UNKNOWN
License: UNKNOWN
Platform: UNKNOWN
